<?xml version="1.0" encoding="UTF-8"?>
<mxGraphModel dx="1394" dy="877" grid="1" gridSize="10" guides="1" tooltips="1" connect="1" arrows="1" fold="1" page="1" pageScale="1" pageWidth="827" pageHeight="1169" math="0" shadow="0"><root><mxCell id="0"/><mxCell id="1" parent="0"/><mxCell id="qV8LfYSnTKEl_Yn3bTk6-223" value="" style="rounded=0;whiteSpace=wrap;html=1;shadow=0;comic=1;strokeWidth=1;fontSize=32;align=center;fillColor=none;" vertex="1" parent="1"><mxGeometry x="70" y="1028" width="756" height="152" as="geometry"/></mxCell><mxCell id="kBfG9OoFqd6qwt7-QaXQ-67" value="Organisation" style="rounded=0;whiteSpace=wrap;html=1;comic=1;fontSize=22;align=left;verticalAlign=top;fillColor=#f5f5f5;strokeColor=#666666;fontColor=#333333;" parent="1" vertex="1"><mxGeometry x="99.5" y="1265" width="610" height="400" as="geometry"/></mxCell><mxCell id="kBfG9OoFqd6qwt7-QaXQ-75" value="" style="rounded=0;whiteSpace=wrap;html=1;shadow=0;glass=0;comic=1;strokeWidth=1;fontSize=32;align=center;" parent="1" vertex="1"><mxGeometry x="113" y="1313" width="580" height="197" as="geometry"/></mxCell><mxCell id="kBfG9OoFqd6qwt7-QaXQ-26" value="IT-Organisation" style="rounded=0;whiteSpace=wrap;html=1;comic=1;fontSize=22;align=left;verticalAlign=top;fillColor=#f5f5f5;strokeColor=#666666;fontColor=#333333;" parent="1" vertex="1"><mxGeometry x="101" y="70" width="610" height="400" as="geometry"/></mxCell><mxCell id="kBfG9OoFqd6qwt7-QaXQ-25" value="" style="group;fontSize=22;" parent="1" vertex="1" connectable="0"><mxGeometry x="395" y="129" width="33" height="321" as="geometry"/></mxCell><mxCell id="kBfG9OoFqd6qwt7-QaXQ-24" value="" style="group;rotation=10;fontSize=22;" parent="kBfG9OoFqd6qwt7-QaXQ-25" vertex="1" connectable="0"><mxGeometry width="33" height="321" as="geometry"/></mxCell><mxCell id="kBfG9OoFqd6qwt7-QaXQ-27" value="Dev" style="rounded=0;whiteSpace=wrap;html=1;comic=1;fontSize=22;align=center;verticalAlign=top;" parent="1" vertex="1"><mxGeometry x="139" y="175" width="212" height="80" as="geometry"/></mxCell><mxCell id="kBfG9OoFqd6qwt7-QaXQ-28" value="&lt;div style=&quot;font-size: 22px;&quot;&gt;Ops (Admins)&lt;br style=&quot;font-size: 22px;&quot;&gt;&lt;/div&gt;" style="rounded=0;whiteSpace=wrap;html=1;comic=1;fontSize=22;align=center;verticalAlign=top;dashed=1;" parent="1" vertex="1"><mxGeometry x="461" y="135" width="210" height="300" as="geometry"/></mxCell><mxCell id="kBfG9OoFqd6qwt7-QaXQ-41" value="IT-Organisation" style="rounded=0;whiteSpace=wrap;html=1;comic=1;fontSize=22;align=left;verticalAlign=top;fillColor=#f5f5f5;strokeColor=#666666;fontColor=#333333;" parent="1" vertex="1"><mxGeometry x="101" y="530" width="610" height="400" as="geometry"/></mxCell><mxCell id="kBfG9OoFqd6qwt7-QaXQ-44" value="Infrastructure as Code, Testautomatisierung, IaaS, PaaS" style="rounded=0;whiteSpace=wrap;html=1;comic=1;fontSize=20;align=center;verticalAlign=top;" parent="1" vertex="1"><mxGeometry x="141" y="805" width="210" height="80" as="geometry"/></mxCell><mxCell id="kBfG9OoFqd6qwt7-QaXQ-45" value="Dev" style="rounded=0;whiteSpace=wrap;html=1;comic=1;fontSize=22;align=center;verticalAlign=top;" parent="1" vertex="1"><mxGeometry x="139" y="635" width="212" height="80" as="geometry"/></mxCell><mxCell id="kBfG9OoFqd6qwt7-QaXQ-46" value="&lt;div style=&quot;font-size: 22px;&quot;&gt;Ops (Admins)&lt;br style=&quot;font-size: 22px;&quot;&gt;&lt;/div&gt;" style="rounded=0;whiteSpace=wrap;html=1;comic=1;fontSize=22;align=center;verticalAlign=top;dashed=1;" parent="1" vertex="1"><mxGeometry x="461" y="595" width="210" height="300" as="geometry"/></mxCell><mxCell id="kBfG9OoFqd6qwt7-QaXQ-47" value="Applikationsbetrieb&lt;font&gt;&lt;br&gt;&lt;/font&gt;&lt;div&gt;&lt;font style=&quot;font-size: 32px&quot;&gt;🛠&lt;/font&gt;&lt;/div&gt;" style="rounded=0;whiteSpace=wrap;html=1;comic=1;fontSize=22;align=center;verticalAlign=top;" parent="1" vertex="1"><mxGeometry x="472" y="635" width="188" height="80" as="geometry"/></mxCell><mxCell id="kBfG9OoFqd6qwt7-QaXQ-48" value="&lt;div&gt;Infrastruktur&lt;/div&gt;&lt;div&gt;&lt;font style=&quot;font-size: 32px&quot;&gt;🛠&lt;/font&gt;&lt;/div&gt;" style="rounded=0;whiteSpace=wrap;html=1;comic=1;fontSize=22;align=center;verticalAlign=top;" parent="1" vertex="1"><mxGeometry x="472" y="804" width="188" height="82" as="geometry"/></mxCell><mxCell id="kBfG9OoFqd6qwt7-QaXQ-50" value="Entwicklung" style="text;html=1;resizable=0;points=[];autosize=1;align=left;verticalAlign=top;spacingTop=-4;fontSize=32;" parent="1" vertex="1"><mxGeometry x="331.5" y="1079.5" width="120" height="30" as="geometry"/></mxCell><mxCell id="kBfG9OoFqd6qwt7-QaXQ-51" value="&lt;div&gt;Infrastructure as Code&lt;/div&gt;" style="text;html=1;resizable=0;points=[];autosize=1;align=left;verticalAlign=top;spacingTop=-4;fontSize=20;" parent="1" vertex="1"><mxGeometry x="156.5" y="1039.5" width="220" height="30" as="geometry"/></mxCell><mxCell id="kBfG9OoFqd6qwt7-QaXQ-52" value="&lt;div&gt;&lt;br&gt;&lt;/div&gt;" style="text;html=1;resizable=0;points=[];autosize=1;align=left;verticalAlign=top;spacingTop=-4;fontSize=32;" parent="1" vertex="1"><mxGeometry x="522.5" y="1029.5" width="20" height="40" as="geometry"/></mxCell><mxCell id="kBfG9OoFqd6qwt7-QaXQ-53" value="Testautomatisierung" style="text;html=1;resizable=0;points=[];autosize=1;align=left;verticalAlign=top;spacingTop=-4;fontSize=20;" parent="1" vertex="1"><mxGeometry x="408" y="1039.5" width="190" height="30" as="geometry"/></mxCell><mxCell id="kBfG9OoFqd6qwt7-QaXQ-54" value="Monitoring/Alerting" style="text;html=1;resizable=0;points=[];autosize=1;align=left;verticalAlign=top;spacingTop=-4;fontSize=20;" parent="1" vertex="1"><mxGeometry x="531" y="1077" width="180" height="30" as="geometry"/></mxCell><mxCell id="kBfG9OoFqd6qwt7-QaXQ-57" value="&lt;font style=&quot;font-size: 22px&quot;&gt;Continuous Integration&lt;br&gt;&lt;/font&gt;" style="text;html=1;resizable=0;points=[];autosize=1;align=left;verticalAlign=top;spacingTop=-4;fontSize=32;" parent="1" vertex="1"><mxGeometry x="79" y="1087" width="230" height="40" as="geometry"/></mxCell><mxCell id="kBfG9OoFqd6qwt7-QaXQ-58" value="&lt;font style=&quot;font-size: 22px&quot;&gt;Continuous Delivery&lt;br&gt;&lt;/font&gt;" style="text;html=1;resizable=0;points=[];autosize=1;align=left;verticalAlign=top;spacingTop=-4;fontSize=32;" parent="1" vertex="1"><mxGeometry x="183" y="1133" width="210" height="40" as="geometry"/></mxCell><mxCell id="kBfG9OoFqd6qwt7-QaXQ-59" value="Was tut DevOps?" style="text;html=1;resizable=0;points=[];autosize=1;align=left;verticalAlign=top;spacingTop=-4;fontSize=32;" parent="1" vertex="1"><mxGeometry x="99.5" y="960.5" width="260" height="40" as="geometry"/></mxCell><mxCell id="kBfG9OoFqd6qwt7-QaXQ-60" value="Wie funktioniert DevOps richtig?" style="text;html=1;resizable=0;points=[];autosize=1;align=left;verticalAlign=top;spacingTop=-4;fontSize=32;" parent="1" vertex="1"><mxGeometry x="101" y="480" width="480" height="40" as="geometry"/></mxCell><mxCell id="kBfG9OoFqd6qwt7-QaXQ-66" value="Was heißt DevOps?" style="text;html=1;resizable=0;points=[];autosize=1;align=left;verticalAlign=top;spacingTop=-4;fontSize=32;" parent="1" vertex="1"><mxGeometry x="98" y="22" width="300" height="40" as="geometry"/></mxCell><mxCell id="kBfG9OoFqd6qwt7-QaXQ-71" value="Warum DevOps?" style="text;html=1;resizable=0;points=[];autosize=1;align=left;verticalAlign=top;spacingTop=-4;fontSize=32;" parent="1" vertex="1"><mxGeometry x="99.5" y="1220" width="260" height="40" as="geometry"/></mxCell><mxCell id="kBfG9OoFqd6qwt7-QaXQ-73" value="Business" style="text;html=1;resizable=0;points=[];autosize=1;align=left;verticalAlign=middle;spacingTop=-4;fontSize=22;" parent="1" vertex="1"><mxGeometry x="163" y="1390.5" width="100" height="30" as="geometry"/></mxCell><mxCell id="kBfG9OoFqd6qwt7-QaXQ-74" value="Dev" style="text;html=1;resizable=0;points=[];autosize=1;align=left;verticalAlign=middle;spacingTop=-4;fontSize=22;" parent="1" vertex="1"><mxGeometry x="387.5" y="1390" width="50" height="30" as="geometry"/></mxCell><mxCell id="kBfG9OoFqd6qwt7-QaXQ-76" value="Ops" style="text;html=1;resizable=0;points=[];autosize=1;align=left;verticalAlign=middle;spacingTop=-4;fontSize=22;" parent="1" vertex="1"><mxGeometry x="582.5" y="1390" width="60" height="30" as="geometry"/></mxCell><mxCell id="kBfG9OoFqd6qwt7-QaXQ-77" value="" style="endArrow=none;html=1;strokeWidth=2;fontSize=22;entryX=0.345;entryY=0.005;entryDx=0;entryDy=0;entryPerimeter=0;" parent="1" target="kBfG9OoFqd6qwt7-QaXQ-75" edge="1"><mxGeometry width="50" height="50" relative="1" as="geometry"><mxPoint x="313" y="1510" as="sourcePoint"/><mxPoint x="153" y="1670" as="targetPoint"/></mxGeometry></mxCell><mxCell id="kBfG9OoFqd6qwt7-QaXQ-79" value="&lt;div&gt;&lt;br&gt;&lt;/div&gt;" style="text;html=1;resizable=0;points=[];align=center;verticalAlign=middle;labelBackgroundColor=#ffffff;fontSize=22;direction=south;" parent="kBfG9OoFqd6qwt7-QaXQ-77" vertex="1" connectable="0"><mxGeometry x="-0.5773" y="2" relative="1" as="geometry"><mxPoint as="offset"/></mxGeometry></mxCell><mxCell id="kBfG9OoFqd6qwt7-QaXQ-78" value="" style="endArrow=none;html=1;strokeWidth=2;fontSize=22;entryX=0.353;entryY=0;entryDx=0;entryDy=0;entryPerimeter=0;exitX=0.679;exitY=1;exitDx=0;exitDy=0;exitPerimeter=0;" parent="1" edge="1" source="kBfG9OoFqd6qwt7-QaXQ-75"><mxGeometry width="50" height="50" relative="1" as="geometry"><mxPoint x="507.5" y="1510" as="sourcePoint"/><mxPoint x="507.5" y="1313" as="targetPoint"/></mxGeometry></mxCell><mxCell id="kBfG9OoFqd6qwt7-QaXQ-80" value="" style="shape=curlyBracket;whiteSpace=wrap;html=1;rounded=1;shadow=0;glass=0;comic=1;strokeColor=#000000;strokeWidth=1;fillColor=none;fontSize=22;align=center;rotation=-90;" parent="1" vertex="1"><mxGeometry x="292" y="1341" width="20" height="377" as="geometry"/></mxCell><mxCell id="kBfG9OoFqd6qwt7-QaXQ-82" value="" style="shape=curlyBracket;whiteSpace=wrap;html=1;rounded=1;shadow=0;glass=0;comic=1;strokeColor=#000000;strokeWidth=1;fillColor=none;fontSize=22;align=center;rotation=-90;" parent="1" vertex="1"><mxGeometry x="502" y="1380" width="20" height="360" as="geometry"/></mxCell><mxCell id="kBfG9OoFqd6qwt7-QaXQ-83" value="Agilität" style="text;html=1;resizable=0;points=[];autosize=1;align=left;verticalAlign=top;spacingTop=-4;fontSize=22;" parent="1" vertex="1"><mxGeometry x="271" y="1573" width="80" height="30" as="geometry"/></mxCell><mxCell id="kBfG9OoFqd6qwt7-QaXQ-84" value="DevOps" style="text;html=1;resizable=0;points=[];autosize=1;align=left;verticalAlign=top;spacingTop=-4;fontSize=22;" parent="1" vertex="1"><mxGeometry x="472" y="1573" width="90" height="30" as="geometry"/></mxCell><mxCell id="kBfG9OoFqd6qwt7-QaXQ-85" value="" style="shape=curlyBracket;whiteSpace=wrap;html=1;rounded=1;shadow=0;glass=0;comic=1;strokeColor=#000000;strokeWidth=1;fillColor=none;fontSize=22;align=center;rotation=-90;" parent="1" vertex="1"><mxGeometry x="393" y="1325" width="20" height="582" as="geometry"/></mxCell><mxCell id="kBfG9OoFqd6qwt7-QaXQ-86" value="Agile Teams mit DevOps-Kompetenz" style="text;html=1;resizable=0;points=[];autosize=1;align=left;verticalAlign=top;spacingTop=-4;fontSize=22;" parent="1" vertex="1"><mxGeometry x="228" y="1630" width="370" height="30" as="geometry"/></mxCell><mxCell id="kBfG9OoFqd6qwt7-QaXQ-87" value="Wie sieht DevOps heute aus?" style="text;html=1;resizable=0;points=[];autosize=1;align=left;verticalAlign=top;spacingTop=-4;fontSize=32;" parent="1" vertex="1"><mxGeometry x="101" y="1710" width="440" height="40" as="geometry"/></mxCell><mxCell id="kBfG9OoFqd6qwt7-QaXQ-97" value="Automatisierte Infrastrukturprovisionierung" style="text;html=1;resizable=0;points=[];autosize=1;align=left;verticalAlign=top;spacingTop=-4;fontSize=22;" parent="1" vertex="1"><mxGeometry x="405.5" y="1127" width="420" height="30" as="geometry"/></mxCell><mxCell id="qV8LfYSnTKEl_Yn3bTk6-29" value="IT-Organisation" style="rounded=0;whiteSpace=wrap;html=1;comic=1;fontSize=22;align=left;verticalAlign=top;fillColor=#f5f5f5;strokeColor=#666666;fontColor=#333333;" vertex="1" parent="1"><mxGeometry x="100" y="1766" width="610" height="420" as="geometry"/></mxCell><mxCell id="qV8LfYSnTKEl_Yn3bTk6-30" value="Dev Team" style="rounded=0;whiteSpace=wrap;html=1;comic=1;fontSize=22;align=left;verticalAlign=top;fontStyle=4" vertex="1" parent="1"><mxGeometry x="113.5" y="1806" width="580" height="360" as="geometry"/></mxCell><mxCell id="qV8LfYSnTKEl_Yn3bTk6-31" value="" style="ellipse;whiteSpace=wrap;html=1;aspect=fixed;rounded=0;shadow=0;glass=0;comic=1;strokeColor=#000000;strokeWidth=1;fillColor=#ffffff;gradientColor=#ffffff;fontSize=22;align=left;" vertex="1" parent="1"><mxGeometry x="161" y="1923" width="40" height="40" as="geometry"/></mxCell><mxCell id="qV8LfYSnTKEl_Yn3bTk6-32" value="" style="ellipse;whiteSpace=wrap;html=1;aspect=fixed;rounded=0;shadow=0;glass=0;comic=1;strokeColor=#000000;strokeWidth=1;fillColor=#ffffff;gradientColor=#ffffff;fontSize=22;align=left;" vertex="1" parent="1"><mxGeometry x="231" y="1900.5" width="40" height="40" as="geometry"/></mxCell><mxCell id="qV8LfYSnTKEl_Yn3bTk6-35" value="" style="ellipse;whiteSpace=wrap;html=1;aspect=fixed;rounded=0;shadow=0;glass=0;comic=1;strokeColor=#000000;strokeWidth=1;fillColor=#ffffff;gradientColor=#ffffff;fontSize=22;align=left;" vertex="1" parent="1"><mxGeometry x="243" y="1968" width="40" height="40" as="geometry"/></mxCell><mxCell id="qV8LfYSnTKEl_Yn3bTk6-36" value="" style="ellipse;whiteSpace=wrap;html=1;aspect=fixed;rounded=0;shadow=0;glass=0;comic=1;strokeColor=#000000;strokeWidth=1;fillColor=#ffffff;gradientColor=#ffffff;fontSize=22;align=left;" vertex="1" parent="1"><mxGeometry x="212" y="2018" width="40" height="40" as="geometry"/></mxCell><mxCell id="qV8LfYSnTKEl_Yn3bTk6-37" value="" style="ellipse;whiteSpace=wrap;html=1;aspect=fixed;rounded=0;shadow=0;glass=0;comic=1;strokeColor=#000000;strokeWidth=1;fillColor=#ffffff;gradientColor=#ffffff;fontSize=22;align=left;" vertex="1" parent="1"><mxGeometry x="136.5" y="1983" width="40" height="40" as="geometry"/></mxCell><mxCell id="qV8LfYSnTKEl_Yn3bTk6-38" value="" style="ellipse;whiteSpace=wrap;html=1;aspect=fixed;rounded=0;shadow=0;glass=0;comic=1;strokeColor=#000000;strokeWidth=1;fillColor=#ffffff;gradientColor=#ffffff;fontSize=22;align=left;" vertex="1" parent="1"><mxGeometry x="139" y="2063" width="40" height="40" as="geometry"/></mxCell><mxCell id="qV8LfYSnTKEl_Yn3bTk6-39" value="" style="ellipse;whiteSpace=wrap;html=1;aspect=fixed;rounded=0;shadow=0;glass=0;comic=1;strokeColor=#000000;strokeWidth=1;fillColor=#ffffff;gradientColor=#ffffff;fontSize=22;align=left;" vertex="1" parent="1"><mxGeometry x="222" y="2083" width="40" height="40" as="geometry"/></mxCell><mxCell id="qV8LfYSnTKEl_Yn3bTk6-40" value="" style="ellipse;whiteSpace=wrap;html=1;aspect=fixed;rounded=0;shadow=0;glass=0;comic=1;strokeColor=#666666;strokeWidth=1;fillColor=#f5f5f5;fontSize=22;align=left;fontColor=#333333;" vertex="1" parent="1"><mxGeometry x="458" y="1861" width="40" height="40" as="geometry"/></mxCell><mxCell id="qV8LfYSnTKEl_Yn3bTk6-41" value="Developers" style="text;html=1;resizable=0;points=[];autosize=1;align=left;verticalAlign=top;spacingTop=-4;fontSize=22;" vertex="1" parent="1"><mxGeometry x="143.5" y="1846" width="130" height="30" as="geometry"/></mxCell><mxCell id="qV8LfYSnTKEl_Yn3bTk6-42" value="" style="ellipse;whiteSpace=wrap;html=1;aspect=fixed;rounded=0;shadow=0;glass=0;comic=1;strokeColor=#82b366;strokeWidth=1;fillColor=#d5e8d4;fontSize=22;align=left;" vertex="1" parent="1"><mxGeometry x="573" y="1881" width="40" height="40" as="geometry"/></mxCell><mxCell id="qV8LfYSnTKEl_Yn3bTk6-43" value="Scrum Master" style="text;html=1;resizable=0;points=[];autosize=1;align=left;verticalAlign=top;spacingTop=-4;fontSize=22;" vertex="1" parent="1"><mxGeometry x="401.5" y="1816" width="150" height="30" as="geometry"/></mxCell><mxCell id="qV8LfYSnTKEl_Yn3bTk6-44" value="Product Owner" style="text;html=1;resizable=0;points=[];autosize=1;align=left;verticalAlign=top;spacingTop=-4;fontSize=22;" vertex="1" parent="1"><mxGeometry x="523" y="1846" width="160" height="30" as="geometry"/></mxCell><mxCell id="qV8LfYSnTKEl_Yn3bTk6-45" value="" style="ellipse;whiteSpace=wrap;html=1;aspect=fixed;rounded=0;shadow=0;glass=0;comic=1;strokeColor=#d79b00;strokeWidth=1;fillColor=#ffe6cc;fontSize=22;align=left;" vertex="1" parent="1"><mxGeometry x="376" y="1968" width="40" height="40" as="geometry"/></mxCell><mxCell id="qV8LfYSnTKEl_Yn3bTk6-46" value="" style="ellipse;whiteSpace=wrap;html=1;aspect=fixed;rounded=0;shadow=0;glass=0;comic=1;strokeColor=#d6b656;strokeWidth=1;fillColor=#fff2cc;fontSize=22;align=left;" vertex="1" parent="1"><mxGeometry x="477" y="2043" width="40" height="40" as="geometry"/></mxCell><mxCell id="qV8LfYSnTKEl_Yn3bTk6-47" value="" style="ellipse;whiteSpace=wrap;html=1;aspect=fixed;rounded=0;shadow=0;glass=0;comic=1;strokeColor=#b85450;strokeWidth=1;fillColor=#f8cecc;fontSize=22;align=left;" vertex="1" parent="1"><mxGeometry x="587.5" y="2118" width="40" height="40" as="geometry"/></mxCell><mxCell id="qV8LfYSnTKEl_Yn3bTk6-48" value="" style="ellipse;whiteSpace=wrap;html=1;aspect=fixed;rounded=0;shadow=0;glass=0;comic=1;strokeColor=#9673a6;strokeWidth=1;fillColor=#e1d5e7;fontSize=22;align=left;" vertex="1" parent="1"><mxGeometry x="358.5" y="2099.5" width="40" height="40" as="geometry"/></mxCell><mxCell id="qV8LfYSnTKEl_Yn3bTk6-49" value="" style="ellipse;whiteSpace=wrap;html=1;aspect=fixed;rounded=0;shadow=0;glass=0;comic=1;strokeColor=#6c8ebf;strokeWidth=1;fillColor=#dae8fc;fontSize=22;align=left;" vertex="1" parent="1"><mxGeometry x="603" y="2006" width="40" height="40" as="geometry"/></mxCell><mxCell id="qV8LfYSnTKEl_Yn3bTk6-69" value="" style="group" vertex="1" connectable="0" parent="1"><mxGeometry x="213" y="2018" width="40" height="40" as="geometry"/></mxCell><mxCell id="qV8LfYSnTKEl_Yn3bTk6-70" value="" style="endArrow=none;html=1;strokeWidth=2;fillColor=#f8cecc;strokeColor=#b85450;" edge="1" parent="qV8LfYSnTKEl_Yn3bTk6-69"><mxGeometry width="50" height="50" relative="1" as="geometry"><mxPoint y="40" as="sourcePoint"/><mxPoint x="40" as="targetPoint"/></mxGeometry></mxCell><mxCell id="qV8LfYSnTKEl_Yn3bTk6-71" value="" style="endArrow=none;html=1;strokeWidth=2;fillColor=#f8cecc;strokeColor=#b85450;" edge="1" parent="qV8LfYSnTKEl_Yn3bTk6-69"><mxGeometry width="50" height="50" relative="1" as="geometry"><mxPoint x="39" y="40" as="sourcePoint"/><mxPoint x="1" as="targetPoint"/></mxGeometry></mxCell><mxCell id="qV8LfYSnTKEl_Yn3bTk6-81" value="" style="group" vertex="1" connectable="0" parent="1"><mxGeometry x="139" y="2063" width="40" height="40" as="geometry"/></mxCell><mxCell id="qV8LfYSnTKEl_Yn3bTk6-82" value="" style="endArrow=none;html=1;strokeWidth=2;fillColor=#f8cecc;strokeColor=#b85450;" edge="1" parent="qV8LfYSnTKEl_Yn3bTk6-81"><mxGeometry width="50" height="50" relative="1" as="geometry"><mxPoint y="40" as="sourcePoint"/><mxPoint x="40" as="targetPoint"/></mxGeometry></mxCell><mxCell id="qV8LfYSnTKEl_Yn3bTk6-83" value="" style="endArrow=none;html=1;strokeWidth=2;fillColor=#f8cecc;strokeColor=#b85450;" edge="1" parent="qV8LfYSnTKEl_Yn3bTk6-81"><mxGeometry width="50" height="50" relative="1" as="geometry"><mxPoint x="39" y="40" as="sourcePoint"/><mxPoint x="1" as="targetPoint"/></mxGeometry></mxCell><mxCell id="qV8LfYSnTKEl_Yn3bTk6-75" value="" style="group" vertex="1" connectable="0" parent="1"><mxGeometry x="222" y="2083" width="40" height="40" as="geometry"/></mxCell><mxCell id="qV8LfYSnTKEl_Yn3bTk6-76" value="" style="endArrow=none;html=1;strokeWidth=2;fillColor=#f8cecc;strokeColor=#b85450;" edge="1" parent="qV8LfYSnTKEl_Yn3bTk6-75"><mxGeometry width="50" height="50" relative="1" as="geometry"><mxPoint y="40" as="sourcePoint"/><mxPoint x="40" as="targetPoint"/></mxGeometry></mxCell><mxCell id="qV8LfYSnTKEl_Yn3bTk6-77" value="" style="endArrow=none;html=1;strokeWidth=2;fillColor=#f8cecc;strokeColor=#b85450;" edge="1" parent="qV8LfYSnTKEl_Yn3bTk6-75"><mxGeometry width="50" height="50" relative="1" as="geometry"><mxPoint x="39" y="40" as="sourcePoint"/><mxPoint x="1" as="targetPoint"/></mxGeometry></mxCell><mxCell id="qV8LfYSnTKEl_Yn3bTk6-98" value="" style="group" vertex="1" connectable="0" parent="1"><mxGeometry x="242.5" y="1968" width="40" height="40" as="geometry"/></mxCell><mxCell id="qV8LfYSnTKEl_Yn3bTk6-99" value="" style="endArrow=none;html=1;strokeWidth=2;fillColor=#f8cecc;strokeColor=#b85450;" edge="1" parent="qV8LfYSnTKEl_Yn3bTk6-98"><mxGeometry width="50" height="50" relative="1" as="geometry"><mxPoint y="40" as="sourcePoint"/><mxPoint x="40" as="targetPoint"/></mxGeometry></mxCell><mxCell id="qV8LfYSnTKEl_Yn3bTk6-100" value="" style="endArrow=none;html=1;strokeWidth=2;fillColor=#f8cecc;strokeColor=#b85450;" edge="1" parent="qV8LfYSnTKEl_Yn3bTk6-98"><mxGeometry width="50" height="50" relative="1" as="geometry"><mxPoint x="39" y="40" as="sourcePoint"/><mxPoint x="1" as="targetPoint"/></mxGeometry></mxCell><mxCell id="qV8LfYSnTKEl_Yn3bTk6-101" value="" style="group" vertex="1" connectable="0" parent="1"><mxGeometry x="136.5" y="1983" width="40" height="40" as="geometry"/></mxCell><mxCell id="qV8LfYSnTKEl_Yn3bTk6-102" value="" style="endArrow=none;html=1;strokeWidth=2;fillColor=#f8cecc;strokeColor=#b85450;" edge="1" parent="qV8LfYSnTKEl_Yn3bTk6-101"><mxGeometry width="50" height="50" relative="1" as="geometry"><mxPoint y="40" as="sourcePoint"/><mxPoint x="40" as="targetPoint"/></mxGeometry></mxCell><mxCell id="qV8LfYSnTKEl_Yn3bTk6-103" value="" style="endArrow=none;html=1;strokeWidth=2;fillColor=#f8cecc;strokeColor=#b85450;" edge="1" parent="qV8LfYSnTKEl_Yn3bTk6-101"><mxGeometry width="50" height="50" relative="1" as="geometry"><mxPoint x="39" y="40" as="sourcePoint"/><mxPoint x="1" as="targetPoint"/></mxGeometry></mxCell><mxCell id="qV8LfYSnTKEl_Yn3bTk6-104" value="IT-Organisation" style="rounded=0;whiteSpace=wrap;html=1;comic=1;fontSize=22;align=left;verticalAlign=top;fillColor=#f5f5f5;strokeColor=#666666;fontColor=#333333;" vertex="1" parent="1"><mxGeometry x="100" y="2286" width="610" height="420" as="geometry"/></mxCell><mxCell id="qV8LfYSnTKEl_Yn3bTk6-105" value="Dev Team" style="rounded=0;whiteSpace=wrap;html=1;comic=1;fontSize=22;align=left;verticalAlign=top;fontStyle=4" vertex="1" parent="1"><mxGeometry x="114" y="2326" width="580" height="360" as="geometry"/></mxCell><mxCell id="qV8LfYSnTKEl_Yn3bTk6-113" value="" style="ellipse;whiteSpace=wrap;html=1;aspect=fixed;rounded=0;shadow=0;glass=0;comic=1;strokeColor=#666666;strokeWidth=1;fillColor=#f5f5f5;fontSize=22;align=left;fontColor=#333333;" vertex="1" parent="1"><mxGeometry x="458" y="2381" width="40" height="40" as="geometry"/></mxCell><mxCell id="qV8LfYSnTKEl_Yn3bTk6-115" value="" style="ellipse;whiteSpace=wrap;html=1;aspect=fixed;rounded=0;shadow=0;glass=0;comic=1;strokeColor=#82b366;strokeWidth=1;fillColor=#d5e8d4;fontSize=22;align=left;" vertex="1" parent="1"><mxGeometry x="573" y="2401" width="40" height="40" as="geometry"/></mxCell><mxCell id="qV8LfYSnTKEl_Yn3bTk6-116" value="Scrum Master" style="text;html=1;resizable=0;points=[];autosize=1;align=left;verticalAlign=top;spacingTop=-4;fontSize=22;" vertex="1" parent="1"><mxGeometry x="401.5" y="2336" width="150" height="30" as="geometry"/></mxCell><mxCell id="qV8LfYSnTKEl_Yn3bTk6-117" value="Product Owner" style="text;html=1;resizable=0;points=[];autosize=1;align=left;verticalAlign=top;spacingTop=-4;fontSize=22;" vertex="1" parent="1"><mxGeometry x="523" y="2366" width="160" height="30" as="geometry"/></mxCell><mxCell id="qV8LfYSnTKEl_Yn3bTk6-144" value="&lt;font style=&quot;font-size: 32px&quot;&gt;Wie funktioniert DevOps richtig?&lt;/font&gt;" style="text;html=1;resizable=0;points=[];autosize=1;align=left;verticalAlign=top;spacingTop=-4;" vertex="1" parent="1"><mxGeometry x="100.5" y="2242" width="480" height="20" as="geometry"/></mxCell><mxCell id="qV8LfYSnTKEl_Yn3bTk6-146" value="" style="verticalLabelPosition=bottom;verticalAlign=top;html=1;shape=mxgraph.basic.pie;startAngle=0.5;endAngle=0.6496054410100788;rounded=0;shadow=0;glass=0;comic=1;strokeColor=#b85450;strokeWidth=1;fillColor=#f8cecc;fontSize=22;align=left;" vertex="1" parent="1"><mxGeometry x="162.5" y="2443" width="40" height="40" as="geometry"/></mxCell><mxCell id="qV8LfYSnTKEl_Yn3bTk6-147" value="" style="verticalLabelPosition=bottom;verticalAlign=top;html=1;shape=mxgraph.basic.pie;startAngle=0.1396324920223451;endAngle=0.7468173254495136;rounded=0;shadow=0;glass=0;comic=1;strokeColor=#000000;strokeWidth=1;fillColor=#ffffff;gradientColor=#ffffff;fontSize=22;align=left;rotation=-90;" vertex="1" parent="1"><mxGeometry x="161" y="2443" width="40" height="40" as="geometry"/></mxCell><mxCell id="qV8LfYSnTKEl_Yn3bTk6-148" value="" style="verticalLabelPosition=bottom;verticalAlign=top;html=1;shape=mxgraph.basic.pie;startAngle=0.14637792145004605;endAngle=0.3896324920223451;rounded=0;shadow=0;glass=0;comic=1;strokeColor=#d6b656;strokeWidth=1;fillColor=#fff2cc;fontSize=22;align=left;rotation=-180;" vertex="1" parent="1"><mxGeometry x="161" y="2443" width="40" height="40" as="geometry"/></mxCell><mxCell id="qV8LfYSnTKEl_Yn3bTk6-149" value="" style="verticalLabelPosition=bottom;verticalAlign=top;html=1;shape=mxgraph.basic.pie;startAngle=0.3585235363196673;endAngle=0.5672992925498727;rounded=0;shadow=0;glass=0;comic=1;strokeColor=#6c8ebf;strokeWidth=1;fillColor=#dae8fc;fontSize=22;align=left;" vertex="1" parent="1"><mxGeometry x="231" y="2420.5" width="40" height="40" as="geometry"/></mxCell><mxCell id="qV8LfYSnTKEl_Yn3bTk6-150" value="" style="verticalLabelPosition=bottom;verticalAlign=top;html=1;shape=mxgraph.basic.pie;startAngle=0.9984085036175459;endAngle=0.6078912138079359;rounded=0;shadow=0;glass=0;comic=1;strokeColor=#000000;strokeWidth=1;fillColor=#ffffff;gradientColor=#ffffff;fontSize=22;align=left;rotation=-90;" vertex="1" parent="1"><mxGeometry x="231" y="2420.5" width="40" height="40" as="geometry"/></mxCell><mxCell id="qV8LfYSnTKEl_Yn3bTk6-151" value="" style="verticalLabelPosition=bottom;verticalAlign=top;html=1;shape=mxgraph.basic.pie;startAngle=0.06992645701258379;endAngle=0.24344062594951216;rounded=0;shadow=0;glass=0;comic=1;strokeColor=#d79b00;strokeWidth=1;fillColor=#ffe6cc;fontSize=22;align=left;rotation=-180;" vertex="1" parent="1"><mxGeometry x="231" y="2420.5" width="40" height="40" as="geometry"/></mxCell><mxCell id="qV8LfYSnTKEl_Yn3bTk6-153" value="" style="verticalLabelPosition=bottom;verticalAlign=top;html=1;shape=mxgraph.basic.pie;startAngle=0.3563042112927343;endAngle=0.9580289579934987;rounded=0;shadow=0;glass=0;comic=1;strokeColor=#000000;strokeWidth=1;fillColor=#ffffff;gradientColor=#ffffff;fontSize=22;align=left;rotation=-90;" vertex="1" parent="1"><mxGeometry x="358.5" y="2620" width="40" height="40" as="geometry"/></mxCell><mxCell id="qV8LfYSnTKEl_Yn3bTk6-154" value="" style="verticalLabelPosition=bottom;verticalAlign=top;html=1;shape=mxgraph.basic.pie;startAngle=0.2021571216913015;endAngle=0.6045423715417149;rounded=0;shadow=0;glass=0;comic=1;strokeColor=#9673a6;strokeWidth=1;fillColor=#e1d5e7;fontSize=22;align=left;rotation=-180;" vertex="1" parent="1"><mxGeometry x="358.5" y="2620" width="40" height="40" as="geometry"/></mxCell><mxCell id="qV8LfYSnTKEl_Yn3bTk6-155" value="" style="verticalLabelPosition=bottom;verticalAlign=top;html=1;shape=mxgraph.basic.pie;startAngle=0.34504361703454833;endAngle=0.7468173254495136;rounded=0;shadow=0;glass=0;comic=1;strokeColor=#b85450;strokeWidth=1;fillColor=#f8cecc;fontSize=22;align=left;" vertex="1" parent="1"><mxGeometry x="587" y="2638" width="40" height="40" as="geometry"/></mxCell><mxCell id="qV8LfYSnTKEl_Yn3bTk6-156" value="" style="verticalLabelPosition=bottom;verticalAlign=top;html=1;shape=mxgraph.basic.pie;startAngle=0.19359868413899878;endAngle=0.5917329654327684;rounded=0;shadow=0;glass=0;comic=1;strokeColor=#000000;strokeWidth=1;fillColor=#ffffff;gradientColor=#ffffff;fontSize=22;align=left;rotation=-90;" vertex="1" parent="1"><mxGeometry x="587" y="2638" width="40" height="40" as="geometry"/></mxCell><mxCell id="qV8LfYSnTKEl_Yn3bTk6-157" value="" style="verticalLabelPosition=bottom;verticalAlign=top;html=1;shape=mxgraph.basic.pie;startAngle=0.2468173254495136;endAngle=0.4380732523341831;rounded=0;shadow=0;glass=0;comic=1;strokeColor=#9673a6;strokeWidth=1;fillColor=#e1d5e7;fontSize=22;align=left;rotation=-180;" vertex="1" parent="1"><mxGeometry x="587" y="2638" width="40" height="40" as="geometry"/></mxCell><mxCell id="qV8LfYSnTKEl_Yn3bTk6-158" value="" style="verticalLabelPosition=bottom;verticalAlign=top;html=1;shape=mxgraph.basic.pie;startAngle=0.5324704699317755;endAngle=0.014285457105234005;rounded=0;shadow=0;glass=0;comic=1;strokeColor=#000000;strokeWidth=1;fillColor=#ffffff;gradientColor=#ffffff;fontSize=22;align=left;" vertex="1" parent="1"><mxGeometry x="602.5" y="2526" width="40" height="40" as="geometry"/></mxCell><mxCell id="qV8LfYSnTKEl_Yn3bTk6-159" value="" style="verticalLabelPosition=bottom;verticalAlign=top;html=1;shape=mxgraph.basic.pie;startAngle=0.6729605819305962;endAngle=0.7824704699317755;rounded=0;shadow=0;glass=0;comic=1;strokeColor=#b85450;strokeWidth=1;fillColor=#f8cecc;fontSize=22;align=left;rotation=-90;" vertex="1" parent="1"><mxGeometry x="602.5" y="2526" width="40" height="40" as="geometry"/></mxCell><mxCell id="qV8LfYSnTKEl_Yn3bTk6-160" value="" style="verticalLabelPosition=bottom;verticalAlign=top;html=1;shape=mxgraph.basic.pie;startAngle=0.5205747559124867;endAngle=0.9211970936297817;rounded=0;shadow=0;glass=0;comic=1;strokeColor=#6c8ebf;strokeWidth=1;fillColor=#dae8fc;fontSize=22;align=left;rotation=-180;" vertex="1" parent="1"><mxGeometry x="602.5" y="2526" width="40" height="40" as="geometry"/></mxCell><mxCell id="qV8LfYSnTKEl_Yn3bTk6-161" value="" style="verticalLabelPosition=bottom;verticalAlign=top;html=1;shape=mxgraph.basic.pie;startAngle=0.5;endAngle=0.6470651994738623;rounded=0;shadow=0;glass=0;comic=1;strokeColor=#d79b00;strokeWidth=1;fillColor=#ffe6cc;fontSize=22;align=left;" vertex="1" parent="1"><mxGeometry x="477" y="2563" width="40" height="40" as="geometry"/></mxCell><mxCell id="qV8LfYSnTKEl_Yn3bTk6-162" value="" style="verticalLabelPosition=bottom;verticalAlign=top;html=1;shape=mxgraph.basic.pie;startAngle=0.3222688415021494;endAngle=0.7468173254495136;rounded=0;shadow=0;glass=0;comic=1;strokeColor=#d6b656;strokeWidth=1;fillColor=#fff2cc;fontSize=22;align=left;rotation=-90;" vertex="1" parent="1"><mxGeometry x="477" y="2563" width="40" height="40" as="geometry"/></mxCell><mxCell id="qV8LfYSnTKEl_Yn3bTk6-163" value="" style="verticalLabelPosition=bottom;verticalAlign=top;html=1;shape=mxgraph.basic.pie;startAngle=0.1445715809024097;endAngle=0.5889038422446764;rounded=0;shadow=0;glass=0;comic=1;strokeColor=#000000;strokeWidth=1;fillColor=#ffffff;gradientColor=#ffffff;fontSize=22;align=left;rotation=-180;" vertex="1" parent="1"><mxGeometry x="477" y="2563" width="40" height="40" as="geometry"/></mxCell><mxCell id="qV8LfYSnTKEl_Yn3bTk6-164" value="" style="verticalLabelPosition=bottom;verticalAlign=top;html=1;shape=mxgraph.basic.pie;startAngle=0.34167527970021233;endAngle=0.5419710420065014;rounded=0;shadow=0;glass=0;comic=1;strokeColor=#6c8ebf;strokeWidth=1;fillColor=#dae8fc;fontSize=22;align=left;" vertex="1" parent="1"><mxGeometry x="376" y="2488" width="40" height="40" as="geometry"/></mxCell><mxCell id="qV8LfYSnTKEl_Yn3bTk6-165" value="" style="verticalLabelPosition=bottom;verticalAlign=top;html=1;shape=mxgraph.basic.pie;startAngle=0.14510256118324447;endAngle=0.5911426855501892;rounded=0;shadow=0;glass=0;comic=1;strokeColor=#d79b00;strokeWidth=1;fillColor=#ffe6cc;fontSize=22;align=left;rotation=-90;" vertex="1" parent="1"><mxGeometry x="376" y="2488" width="40" height="40" as="geometry"/></mxCell><mxCell id="qV8LfYSnTKEl_Yn3bTk6-166" value="" style="verticalLabelPosition=bottom;verticalAlign=top;html=1;shape=mxgraph.basic.pie;startAngle=0.03748814800221059;endAngle=0.4031240879316606;rounded=0;shadow=0;glass=0;comic=1;strokeWidth=1;fontSize=22;align=left;rotation=-180;" vertex="1" parent="1"><mxGeometry x="376" y="2488" width="40" height="40" as="geometry"/></mxCell><mxCell id="qV8LfYSnTKEl_Yn3bTk6-172" value="&lt;div&gt;Performance&lt;/div&gt;&lt;div align=&quot;center&quot;&gt;Champion&lt;br&gt;&lt;/div&gt;" style="text;html=1;resizable=0;points=[];autosize=1;align=center;verticalAlign=top;spacingTop=-4;fontSize=22;" vertex="1" parent="1"><mxGeometry x="320" y="2433" width="140" height="50" as="geometry"/></mxCell><mxCell id="qV8LfYSnTKEl_Yn3bTk6-173" value="&lt;div&gt;UX&lt;/div&gt;&lt;div&gt;Champion&lt;/div&gt;" style="text;html=1;resizable=0;points=[];autosize=1;align=center;verticalAlign=top;spacingTop=-4;fontSize=22;" vertex="1" parent="1"><mxGeometry x="441" y="2509" width="110" height="50" as="geometry"/></mxCell><mxCell id="qV8LfYSnTKEl_Yn3bTk6-174" value="&lt;div&gt;DevOps&lt;/div&gt;&lt;div&gt;Champion&lt;br&gt;&lt;/div&gt;" style="text;html=1;resizable=0;points=[];autosize=1;align=center;verticalAlign=top;spacingTop=-4;fontSize=22;" vertex="1" parent="1"><mxGeometry x="568" y="2473" width="110" height="50" as="geometry"/></mxCell><mxCell id="qV8LfYSnTKEl_Yn3bTk6-175" value="&lt;div&gt;Security&lt;/div&gt;&lt;div&gt;Champion&lt;br&gt;&lt;/div&gt;" style="text;html=1;resizable=0;points=[];autosize=1;align=center;verticalAlign=top;spacingTop=-4;fontSize=22;" vertex="1" parent="1"><mxGeometry x="553.5" y="2584.5" width="110" height="50" as="geometry"/></mxCell><mxCell id="qV8LfYSnTKEl_Yn3bTk6-176" value="&lt;div&gt;QA&lt;/div&gt;&lt;div&gt;Champion&lt;br&gt;&lt;/div&gt;" style="text;html=1;resizable=0;points=[];autosize=1;align=center;verticalAlign=top;spacingTop=-4;fontSize=22;" vertex="1" parent="1"><mxGeometry x="322.5" y="2566.5" width="110" height="50" as="geometry"/></mxCell><mxCell id="qV8LfYSnTKEl_Yn3bTk6-194" value="&lt;div&gt;Performance&lt;/div&gt;&lt;div align=&quot;center&quot;&gt;&lt;br&gt;&lt;/div&gt;" style="text;html=1;resizable=0;points=[];autosize=1;align=center;verticalAlign=top;spacingTop=-4;fontSize=22;" vertex="1" parent="1"><mxGeometry x="320" y="1913" width="140" height="50" as="geometry"/></mxCell><mxCell id="qV8LfYSnTKEl_Yn3bTk6-195" value="&lt;div&gt;UX&lt;/div&gt;&lt;div&gt;&lt;br&gt;&lt;/div&gt;" style="text;html=1;resizable=0;points=[];autosize=1;align=center;verticalAlign=top;spacingTop=-4;fontSize=22;" vertex="1" parent="1"><mxGeometry x="441" y="1989" width="110" height="50" as="geometry"/></mxCell><mxCell id="qV8LfYSnTKEl_Yn3bTk6-196" value="&lt;div&gt;DevOps&lt;/div&gt;&lt;div&gt;&lt;br&gt;&lt;/div&gt;" style="text;html=1;resizable=0;points=[];autosize=1;align=center;verticalAlign=top;spacingTop=-4;fontSize=22;" vertex="1" parent="1"><mxGeometry x="568" y="1953" width="110" height="50" as="geometry"/></mxCell><mxCell id="qV8LfYSnTKEl_Yn3bTk6-197" value="&lt;div&gt;Security&lt;/div&gt;&lt;div&gt;&lt;br&gt;&lt;/div&gt;" style="text;html=1;resizable=0;points=[];autosize=1;align=center;verticalAlign=top;spacingTop=-4;fontSize=22;" vertex="1" parent="1"><mxGeometry x="553.5" y="2064.5" width="110" height="50" as="geometry"/></mxCell><mxCell id="qV8LfYSnTKEl_Yn3bTk6-198" value="&lt;div&gt;QA&lt;/div&gt;&lt;div&gt;&lt;br&gt;&lt;/div&gt;" style="text;html=1;resizable=0;points=[];autosize=1;align=center;verticalAlign=top;spacingTop=-4;fontSize=22;" vertex="1" parent="1"><mxGeometry x="322.5" y="2046.5" width="110" height="50" as="geometry"/></mxCell><mxCell id="qV8LfYSnTKEl_Yn3bTk6-212" value="🧱🧱🧱🧱🧱🧱🧱🧱" style="text;html=1;resizable=0;points=[];autosize=1;align=left;verticalAlign=top;spacingTop=-4;fontSize=32;spacing=2;spacingBottom=0;horizontal=0;" vertex="1" parent="1"><mxGeometry x="388" y="117" width="50" height="330" as="geometry"/></mxCell><mxCell id="qV8LfYSnTKEl_Yn3bTk6-215" value="🧱🧱🧱🧱🧱🧱🧱🧱" style="text;html=1;resizable=0;points=[];autosize=1;align=left;verticalAlign=top;spacingTop=-4;fontSize=32;spacing=2;spacingBottom=0;horizontal=0;" vertex="1" parent="1"><mxGeometry x="388" y="127" width="50" height="330" as="geometry"/></mxCell><mxCell id="qV8LfYSnTKEl_Yn3bTk6-211" value="" style="curved=1;endArrow=classic;html=1;strokeWidth=2;exitX=1;exitY=0.5;exitDx=0;exitDy=0;entryX=0;entryY=0.25;entryDx=0;entryDy=0;" edge="1" parent="1" source="kBfG9OoFqd6qwt7-QaXQ-27" target="kBfG9OoFqd6qwt7-QaXQ-28"><mxGeometry width="50" height="50" relative="1" as="geometry"><mxPoint x="370" y="250" as="sourcePoint"/><mxPoint x="420" y="200" as="targetPoint"/><Array as="points"><mxPoint x="400" y="170"/></Array></mxGeometry></mxCell><mxCell id="qV8LfYSnTKEl_Yn3bTk6-217" value="" style="rounded=0;whiteSpace=wrap;html=1;shadow=0;glass=0;comic=1;fontSize=22;rotation=10;" vertex="1" parent="1"><mxGeometry x="375" y="139" width="31" height="40" as="geometry"/></mxCell><mxCell id="qV8LfYSnTKEl_Yn3bTk6-216" value="" style="rounded=0;whiteSpace=wrap;html=1;shadow=0;glass=0;comic=1;fontSize=22;rotation=10;" vertex="1" parent="1"><mxGeometry x="371" y="134" width="31" height="40" as="geometry"/></mxCell><mxCell id="kBfG9OoFqd6qwt7-QaXQ-20" value="" style="rounded=0;whiteSpace=wrap;html=1;shadow=0;glass=0;comic=1;fontSize=22;rotation=10;" parent="1" vertex="1"><mxGeometry x="367" y="129" width="31" height="40" as="geometry"/></mxCell><mxCell id="kBfG9OoFqd6qwt7-QaXQ-42" value="Infrastructure DevOps &lt;font style=&quot;font-size: 32px&quot;&gt;🤖&lt;/font&gt;" style="rounded=0;whiteSpace=wrap;html=1;comic=1;fontSize=22;align=left;verticalAlign=top;fillColor=none;strokeColor=#006600;strokeWidth=3;" parent="1" vertex="1"><mxGeometry x="123" y="755" width="570" height="150" as="geometry"/></mxCell><mxCell id="kBfG9OoFqd6qwt7-QaXQ-43" value="Application DevOps &lt;font style=&quot;font-size: 32px&quot;&gt;🤖&lt;/font&gt;" style="rounded=0;whiteSpace=wrap;html=1;comic=1;fontSize=22;align=left;verticalAlign=top;fillColor=none;strokeColor=#006600;strokeWidth=3;" parent="1" vertex="1"><mxGeometry x="123" y="585" width="570" height="150" as="geometry"/></mxCell></root></mxGraphModel>